odoo/addons/fetchmail_incoming_log_test/README.rst
odoo/addons/fetchmail_incoming_log_test/__init__.py
odoo/addons/fetchmail_incoming_log_test/__manifest__.py
odoo/addons/fetchmail_incoming_log_test/i18n/fetchmail_incoming_log_test.pot
odoo/addons/fetchmail_incoming_log_test/readme/CONTRIBUTORS.rst
odoo/addons/fetchmail_incoming_log_test/readme/DESCRIPTION.rst
odoo/addons/fetchmail_incoming_log_test/static/description/icon.png
odoo/addons/fetchmail_incoming_log_test/static/description/index.html
odoo/addons/fetchmail_incoming_log_test/tests/__init__.py
odoo/addons/fetchmail_incoming_log_test/tests/test_fetchmail_incoming_log.py
odoo_addon_fetchmail_incoming_log_test-15.0.1.0.0.3.dist-info/METADATA
odoo_addon_fetchmail_incoming_log_test-15.0.1.0.0.3.dist-info/WHEEL
odoo_addon_fetchmail_incoming_log_test-15.0.1.0.0.3.dist-info/top_level.txt
odoo_addon_fetchmail_incoming_log_test-15.0.1.0.0.3.dist-info/RECORD
